MANIFEST.in
README.md
setup.py
.tox/py36/lib/python3.6/site-packages/Cython/Compiler/Code.pxd
.tox/py36/lib/python3.6/site-packages/Cython/Compiler/FlowControl.pxd
.tox/py36/lib/python3.6/site-packages/Cython/Compiler/ParseTreeTransforms.pxd
.tox/py36/lib/python3.6/site-packages/Cython/Compiler/Parsing.pxd
.tox/py36/lib/python3.6/site-packages/Cython/Compiler/Scanning.pxd
.tox/py36/lib/python3.6/site-packages/Cython/Compiler/Visitor.pxd
.tox/py36/lib/python3.6/site-packages/Cython/Includes/openmp.pxd
.tox/py36/lib/python3.6/site-packages/Cython/Includes/Deprecated/python.pxd
.tox/py36/lib/python3.6/site-packages/Cython/Includes/Deprecated/python_bool.pxd
.tox/py36/lib/python3.6/site-packages/Cython/Includes/Deprecated/python_buffer.pxd
.tox/py36/lib/python3.6/site-packages/Cython/Includes/Deprecated/python_bytes.pxd
.tox/py36/lib/python3.6/site-packages/Cython/Includes/Deprecated/python_cobject.pxd
.tox/py36/lib/python3.6/site-packages/Cython/Includes/Deprecated/python_complex.pxd
.tox/py36/lib/python3.6/site-packages/Cython/Includes/Deprecated/python_dict.pxd
.tox/py36/lib/python3.6/site-packages/Cython/Includes/Deprecated/python_exc.pxd
.tox/py36/lib/python3.6/site-packages/Cython/Includes/Deprecated/python_float.pxd
.tox/py36/lib/python3.6/site-packages/Cython/Includes/Deprecated/python_function.pxd
.tox/py36/lib/python3.6/site-packages/Cython/Includes/Deprecated/python_getargs.pxd
.tox/py36/lib/python3.6/site-packages/Cython/Includes/Deprecated/python_instance.pxd
.tox/py36/lib/python3.6/site-packages/Cython/Includes/Deprecated/python_int.pxd
.tox/py36/lib/python3.6/site-packages/Cython/Includes/Deprecated/python_iterator.pxd
.tox/py36/lib/python3.6/site-packages/Cython/Includes/Deprecated/python_list.pxd
.tox/py36/lib/python3.6/site-packages/Cython/Includes/Deprecated/python_long.pxd
.tox/py36/lib/python3.6/site-packages/Cython/Includes/Deprecated/python_mapping.pxd
.tox/py36/lib/python3.6/site-packages/Cython/Includes/Deprecated/python_mem.pxd
atomic_sequence.egg-info/PKG-INFO
atomic_sequence.egg-info/SOURCES.txt
atomic_sequence.egg-info/dependency_links.txt
atomic_sequence.egg-info/top_level.txt
