Metadata-Version: 2.1
Name: atomic-sequence
Version: 0.0.8
Summary: A lock-free, thread-safe sequence counter using the C++ atomic library.
Home-page: https://github.com/arossoshynskyy/atomic-sequence
Author: Andriy Rossoshynskyy
Author-email: andriy.rossoshynskyy@gmail.com
License: UNKNOWN
Platform: UNKNOWN
Classifier: Programming Language :: Python :: 3
Classifier: License :: OSI Approved :: MIT License
Requires-Python: >=3.6
